README.md
setup.py
singlesday.py
singlesday.egg-info/PKG-INFO
singlesday.egg-info/SOURCES.txt
singlesday.egg-info/dependency_links.txt
singlesday.egg-info/entry_points.txt
singlesday.egg-info/top_level.txt